{
  "db_name": "PostgreSQL",
  "query": "SELECT worker_id, public_key FROM worker_identities WHERE active",
  "describe": {
    "columns": [
      {
        "ordinal": 0,
        "name": "worker_id",
        "type_info": "Text"
      },
      {
        "ordinal": 1,
        "name": "public_key",
        "type_info": "Bytea"
      }
    ],
    "parameters": {
      "Left": []
    },
    "nullable": [
      false,
      false
    ]
  },
  "hash": "d60cd4752875249408b603c79742bbd6367434e5807cd7417e64a8988c5f0d2e"
}
